[{"name":"instructor-framework","description":null,"location":"index.html","searchKeys":["instructor-framework"]},{"name":"io.github.uinnn.instructor","description":null,"location":"instructor-framework/io.github.uinnn.instructor/index.html","searchKeys":["io.github.uinnn.instructor"]},{"name":"Argumentable","description":null,"location":"instructor-framework/io.github.uinnn.instructor/-argumentable/index.html","searchKeys":["Argumentable"]},{"name":"array()","description":null,"location":"instructor-framework/io.github.uinnn.instructor/array.html","searchKeys":["array()"]},{"name":"asFluent()","description":null,"location":"instructor-framework/io.github.uinnn.instructor/as-fluent.html","searchKeys":["asFluent()"]},{"name":"asIterable()","description":null,"location":"instructor-framework/io.github.uinnn.instructor/as-iterable.html","searchKeys":["asIterable()"]},{"name":"asList()","description":null,"location":"instructor-framework/io.github.uinnn.instructor/as-list.html","searchKeys":["asList()"]},{"name":"asSequence()","description":null,"location":"instructor-framework/io.github.uinnn.instructor/as-sequence.html","searchKeys":["asSequence()"]},{"name":"attemptPerform()","description":null,"location":"instructor-framework/io.github.uinnn.instructor/attempt-perform.html","searchKeys":["attemptPerform()"]},{"name":"boolean()","description":null,"location":"instructor-framework/io.github.uinnn.instructor/boolean.html","searchKeys":["boolean()"]},{"name":"byte()","description":null,"location":"instructor-framework/io.github.uinnn.instructor/byte.html","searchKeys":["byte()"]},{"name":"commandMap","description":null,"location":"instructor-framework/io.github.uinnn.instructor/command-map.html","searchKeys":["commandMap"]},{"name":"contains()","description":null,"location":"instructor-framework/io.github.uinnn.instructor/contains.html","searchKeys":["contains()"]},{"name":"double()","description":null,"location":"instructor-framework/io.github.uinnn.instructor/double.html","searchKeys":["double()"]},{"name":"error()","description":null,"location":"instructor-framework/io.github.uinnn.instructor/error.html","searchKeys":["error()"]},{"name":"float()","description":null,"location":"instructor-framework/io.github.uinnn.instructor/float.html","searchKeys":["float()"]},{"name":"gamemode()","description":null,"location":"instructor-framework/io.github.uinnn.instructor/gamemode.html","searchKeys":["gamemode()"]},{"name":"Instructable","description":null,"location":"instructor-framework/io.github.uinnn.instructor/-instructable/index.html","searchKeys":["Instructable"]},{"name":"Instructor","description":null,"location":"instructor-framework/io.github.uinnn.instructor/-instructor/index.html","searchKeys":["Instructor"]},{"name":"instructor","description":null,"location":"instructor-framework/io.github.uinnn.instructor/instructor.html","searchKeys":["instructor"]},{"name":"InstructorError","description":null,"location":"instructor-framework/io.github.uinnn.instructor/-instructor-error/index.html","searchKeys":["InstructorError"]},{"name":"InstructorPerformer","description":null,"location":"instructor-framework/io.github.uinnn.instructor/-instructor-performer/index.html","searchKeys":["InstructorPerformer"]},{"name":"instructorWith","description":null,"location":"instructor-framework/io.github.uinnn.instructor/instructor-with.html","searchKeys":["instructorWith"]},{"name":"int()","description":null,"location":"instructor-framework/io.github.uinnn.instructor/int.html","searchKeys":["int()"]},{"name":"join()","description":null,"location":"instructor-framework/io.github.uinnn.instructor/join.html","searchKeys":["join()"]},{"name":"knownCommands","description":null,"location":"instructor-framework/io.github.uinnn.instructor/known-commands.html","searchKeys":["knownCommands"]},{"name":"lastIndex","description":null,"location":"instructor-framework/io.github.uinnn.instructor/last-index.html","searchKeys":["lastIndex"]},{"name":"list()","description":null,"location":"instructor-framework/io.github.uinnn.instructor/list.html","searchKeys":["list()"]},{"name":"long()","description":null,"location":"instructor-framework/io.github.uinnn.instructor/long.html","searchKeys":["long()"]},{"name":"lowercase()","description":null,"location":"instructor-framework/io.github.uinnn.instructor/lowercase.html","searchKeys":["lowercase()"]},{"name":"map()","description":null,"location":"instructor-framework/io.github.uinnn.instructor/map.html","searchKeys":["map()"]},{"name":"offlinePlayer()","description":null,"location":"instructor-framework/io.github.uinnn.instructor/offline-player.html","searchKeys":["offlinePlayer()"]},{"name":"optionalArray()","description":null,"location":"instructor-framework/io.github.uinnn.instructor/optional-array.html","searchKeys":["optionalArray()"]},{"name":"optionalBoolean()","description":null,"location":"instructor-framework/io.github.uinnn.instructor/optional-boolean.html","searchKeys":["optionalBoolean()"]},{"name":"optionalByte()","description":null,"location":"instructor-framework/io.github.uinnn.instructor/optional-byte.html","searchKeys":["optionalByte()"]},{"name":"optionalDouble()","description":null,"location":"instructor-framework/io.github.uinnn.instructor/optional-double.html","searchKeys":["optionalDouble()"]},{"name":"optionalFloat()","description":null,"location":"instructor-framework/io.github.uinnn.instructor/optional-float.html","searchKeys":["optionalFloat()"]},{"name":"optionalGamemode()","description":null,"location":"instructor-framework/io.github.uinnn.instructor/optional-gamemode.html","searchKeys":["optionalGamemode()"]},{"name":"optionalInt()","description":null,"location":"instructor-framework/io.github.uinnn.instructor/optional-int.html","searchKeys":["optionalInt()"]},{"name":"optionalList()","description":null,"location":"instructor-framework/io.github.uinnn.instructor/optional-list.html","searchKeys":["optionalList()"]},{"name":"optionalLong()","description":null,"location":"instructor-framework/io.github.uinnn.instructor/optional-long.html","searchKeys":["optionalLong()"]},{"name":"optionalOfflinePlayer()","description":null,"location":"instructor-framework/io.github.uinnn.instructor/optional-offline-player.html","searchKeys":["optionalOfflinePlayer()"]},{"name":"optionalPlayer()","description":null,"location":"instructor-framework/io.github.uinnn.instructor/optional-player.html","searchKeys":["optionalPlayer()"]},{"name":"optionalShort()","description":null,"location":"instructor-framework/io.github.uinnn.instructor/optional-short.html","searchKeys":["optionalShort()"]},{"name":"player()","description":null,"location":"instructor-framework/io.github.uinnn.instructor/player.html","searchKeys":["player()"]},{"name":"register()","description":null,"location":"instructor-framework/io.github.uinnn.instructor/register.html","searchKeys":["register()"]},{"name":"send()","description":null,"location":"instructor-framework/io.github.uinnn.instructor/send.html","searchKeys":["send()"]},{"name":"SenderType","description":null,"location":"instructor-framework/io.github.uinnn.instructor/-sender-type/index.html","searchKeys":["SenderType"]},{"name":"BOTH","description":null,"location":"instructor-framework/io.github.uinnn.instructor/-sender-type/-b-o-t-h/index.html","searchKeys":["BOTH"]},{"name":"CONSOLE","description":null,"location":"instructor-framework/io.github.uinnn.instructor/-sender-type/-c-o-n-s-o-l-e/index.html","searchKeys":["CONSOLE"]},{"name":"PLAYER","description":null,"location":"instructor-framework/io.github.uinnn.instructor/-sender-type/-p-l-a-y-e-r/index.html","searchKeys":["PLAYER"]},{"name":"short()","description":null,"location":"instructor-framework/io.github.uinnn.instructor/short.html","searchKeys":["short()"]},{"name":"size","description":null,"location":"instructor-framework/io.github.uinnn.instructor/size.html","searchKeys":["size"]},{"name":"StandardInstructorPerformer","description":null,"location":"instructor-framework/io.github.uinnn.instructor/-standard-instructor-performer/index.html","searchKeys":["StandardInstructorPerformer"]},{"name":"unregister()","description":null,"location":"instructor-framework/io.github.uinnn.instructor/unregister.html","searchKeys":["unregister()"]},{"name":"uppercase()","description":null,"location":"instructor-framework/io.github.uinnn.instructor/uppercase.html","searchKeys":["uppercase()"]},{"name":"validate()","description":null,"location":"instructor-framework/io.github.uinnn.instructor/validate.html","searchKeys":["validate()"]},{"name":"validateNot()","description":null,"location":"instructor-framework/io.github.uinnn.instructor/validate-not.html","searchKeys":["validateNot()"]},{"name":"io.github.uinnn.instructor.common","description":null,"location":"instructor-framework/io.github.uinnn.instructor.common/index.html","searchKeys":["io.github.uinnn.instructor.common"]},{"name":"or()","description":null,"location":"instructor-framework/io.github.uinnn.instructor.common/or.html","searchKeys":["or()"]},{"name":"toInstructor()","description":null,"location":"instructor-framework/io.github.uinnn.instructor.common/to-instructor.html","searchKeys":["toInstructor()"]}]
